py-mathtest/__init__.py
py-mathtest/simple_maths_questions.py
pymathtest/__init__.py
pymathtest/simple_maths_questions.py
pymathtest-0.1.1.dev4.dist-info/METADATA
pymathtest-0.1.1.dev4.dist-info/WHEEL
pymathtest-0.1.1.dev4.dist-info/top_level.txt
pymathtest-0.1.1.dev4.dist-info/RECORD
