Metadata-Version: 2.1
Name: pymathtest
Version: 0.1.1.dev4
Summary: A tool that can randomly generates simple add and subtract questions.
Home-page: https://github.com/whattobuild/pymathtest
Author: Telon Chyi
Author-email: laoqizhuzhanghaoyong02@outlook.com
License: UNKNOWN
Keywords: maths question python
Platform: UNKNOWN
Classifier: Operating System :: OS Independent
Classifier: License :: OSI Approved :: MIT License
Classifier: Programming Language :: Python :: 3
Requires-Python: >=3.4
